<annotation>
	<folder>所有改尺寸水平翻转</folder>
	<filename>s-b32.jpg</filename>
	<path>C:\Users\Yu\Desktop\laji\所有改尺寸水平翻转\s-b32.jpg</path>
	<source>
		<database>Unknown</database>
	</source>
	<size>
		<width>640</width>
		<height>468</height>
		<depth>3</depth>
	</size>
	<segmented>0</segmented>
	<object>
		<name>plastic film</name>
		<pose>Unspecified</pose>
		<truncated>0</truncated>
		<difficult>0</difficult>
		<bndbox>
			<xmin>224</xmin>
			<ymin>173</ymin>
			<xmax>306</xmax>
			<ymax>306</ymax>
		</bndbox>
	</object>
	<object>
		<name>plastic film</name>
		<pose>Unspecified</pose>
		<truncated>0</truncated>
		<difficult>0</difficult>
		<bndbox>
			<xmin>368</xmin>
			<ymin>204</ymin>
			<xmax>463</xmax>
			<ymax>276</ymax>
		</bndbox>
	</object>
</annotation>
